utils_uiauto/__init__.py
utils_uiauto/ie.py
utils_uiauto/driver/__init__.py
utils_uiauto/driver/dd_code.py
utils_uiauto/driver/dd_driver.py
utils_uiauto/driver/__pycache__/__init__.cpython-311.pyc
utils_uiauto/driver/__pycache__/dd_code.cpython-311.pyc
utils_uiauto/driver/__pycache__/dd_driver.cpython-311.pyc
utils_uiauto/driver/dll/1.Simple/DD94687.32.dll
utils_uiauto/driver/dll/1.Simple/DD94687.64.dll
utils_uiauto/driver/dll/2.General/DD32.dll
utils_uiauto/driver/dll/2.General/DD64.dll
utils_uiauto/driver/dll/2.General/drv.win10/dc64.exe
utils_uiauto/driver/dll/2.General/drv.win10/dd.key.94396.cat
utils_uiauto/driver/dll/2.General/drv.win10/dd.key.94396.inf
utils_uiauto/driver/dll/2.General/drv.win10/dd.key.94396.sys
utils_uiauto/driver/dll/2.General/drv.win10/dd.mou.94396.cat
utils_uiauto/driver/dll/2.General/drv.win10/dd.mou.94396.inf
utils_uiauto/driver/dll/2.General/drv.win10/dd.mou.94396.sys
utils_uiauto/driver/dll/2.General/drv.win10/setup.cmd
utils_uiauto/driver/dll/2.General/drv.win7/dc64.exe
utils_uiauto/driver/dll/2.General/drv.win7/dd.key.94396.cat
utils_uiauto/driver/dll/2.General/drv.win7/dd.key.94396.inf
utils_uiauto/driver/dll/2.General/drv.win7/dd.key.94396.sys
utils_uiauto/driver/dll/2.General/drv.win7/dd.mou.94396.cat
utils_uiauto/driver/dll/2.General/drv.win7/dd.mou.94396.inf
utils_uiauto/driver/dll/2.General/drv.win7/dd.mou.94396.sys
utils_uiauto/driver/dll/2.General/drv.win7/setup.cmd
utils_uiauto/driver/dll/3.HID/DDHID32.dll
utils_uiauto/driver/dll/3.HID/DDHID64.dll
utils_uiauto/driver/dll/3.HID/h.bmp
utils_uiauto/driver/dll/3.HID/drv.win10/64.exe
utils_uiauto/driver/dll/3.HID/drv.win10/DDHID1906.cat
utils_uiauto/driver/dll/3.HID/drv.win10/DDHID1906.inf
utils_uiauto/driver/dll/3.HID/drv.win10/DDHID1906.sys
utils_uiauto/driver/dll/3.HID/drv.win10/install.cmd
utils_uiauto/driver/dll/3.HID/drv.win10/uninstall.cmd
utils_uiauto/driver/dll/3.HID/drv.win7/64.exe
utils_uiauto/driver/dll/3.HID/drv.win7/DDHID1906.cat
utils_uiauto-0.4.0.dist-info/LICENSE.txt
utils_uiauto-0.4.0.dist-info/METADATA
utils_uiauto-0.4.0.dist-info/WHEEL
utils_uiauto-0.4.0.dist-info/top_level.txt
utils_uiauto-0.4.0.dist-info/RECORD
