Metadata-Version: 2.1
Name: utils-uiauto
Version: 0.4.0
Summary: uiautomation utils and rpa utils
Home-page: https://github.com/Ly-star-bit/utils_uiauto.git
Author: Yu
Author-email: a13376657928@gmail.com
License: MIT
Classifier: License :: OSI Approved :: MIT License
Classifier: Programming Language :: Python
Classifier: Programming Language :: Python :: 3
Classifier: Programming Language :: Python :: 3.7
Classifier: Programming Language :: Python :: Implementation :: CPython
Classifier: Programming Language :: Python :: Implementation :: PyPy
Requires-Python: >=3.7.0
License-File: LICENSE.txt
Requires-Dist: retrying
Requires-Dist: pathlib
Requires-Dist: uiautomation
Provides-Extra: dd
Requires-Dist: retrying ; extra == 'dd'
Requires-Dist: pathlib ; extra == 'dd'
Provides-Extra: ie
Requires-Dist: uiautomation ; extra == 'ie'
